BeautifulSoup420ZhongwenWendang/README.md
BeautifulSoup420ZhongwenWendang/__init__.py
BeautifulSoup420ZhongwenWendang/__main__.py
BeautifulSoup420ZhongwenWendang/file.epub
BeautifulSoup420ZhongwenWendang/index.html
BeautifulSoup420ZhongwenWendang/css/__init__.py
BeautifulSoup420ZhongwenWendang/css/annotations.css
BeautifulSoup420ZhongwenWendang/css/main.css
BeautifulSoup420ZhongwenWendang/css/normalize.css
BeautifulSoup420ZhongwenWendang/css/popup.css
BeautifulSoup420ZhongwenWendang/font/__init__.py
BeautifulSoup420ZhongwenWendang/font/fontello.eot
BeautifulSoup420ZhongwenWendang/font/fontello.svg
BeautifulSoup420ZhongwenWendang/font/fontello.ttf
BeautifulSoup420ZhongwenWendang/font/fontello.woff
BeautifulSoup420ZhongwenWendang/img/__init__.py
BeautifulSoup420ZhongwenWendang/img/annotator-glyph-sprite.png
BeautifulSoup420ZhongwenWendang/img/annotator-icon-sprite.png
BeautifulSoup420ZhongwenWendang/img/apple-touch-icon.png
BeautifulSoup420ZhongwenWendang/img/cancelfullscreen.png
BeautifulSoup420ZhongwenWendang/img/close.png
BeautifulSoup420ZhongwenWendang/img/fullscreen.png
BeautifulSoup420ZhongwenWendang/img/loader.gif
BeautifulSoup420ZhongwenWendang/img/menu-icon.png
BeautifulSoup420ZhongwenWendang/img/save.png
BeautifulSoup420ZhongwenWendang/img/saved.png
BeautifulSoup420ZhongwenWendang/img/settings-s.png
BeautifulSoup420ZhongwenWendang/img/settings.png
BeautifulSoup420ZhongwenWendang/img/star.png
BeautifulSoup420ZhongwenWendang/js/__init__.py
BeautifulSoup420ZhongwenWendang/js/epub.js
BeautifulSoup420ZhongwenWendang/js/epub.min.js
BeautifulSoup420ZhongwenWendang/js/epub.min.map
BeautifulSoup420ZhongwenWendang/js/hooks.min.js
BeautifulSoup420ZhongwenWendang/js/hooks.min.map
BeautifulSoup420ZhongwenWendang/js/reader.js
BeautifulSoup420ZhongwenWendang/js/reader.js.map
BeautifulSoup420ZhongwenWendang/js/reader.min.js
BeautifulSoup420ZhongwenWendang/js/reader.min.map
BeautifulSoup420ZhongwenWendang/js/hooks/__init__.py
beautiful_soup_4_2_0_zhongwen_wendang-2024.3.1.0.dist-info/METADATA
beautiful_soup_4_2_0_zhongwen_wendang-2024.3.1.0.dist-info/WHEEL
beautiful_soup_4_2_0_zhongwen_wendang-2024.3.1.0.dist-info/entry_points.txt
beautiful_soup_4_2_0_zhongwen_wendang-2024.3.1.0.dist-info/top_level.txt
beautiful_soup_4_2_0_zhongwen_wendang-2024.3.1.0.dist-info/RECORD
